langextract_litellm/__init__.py
langextract_litellm/provider.py
langextract_litellm-0.1.0.dist-info/licenses/LICENSE
langextract_litellm-0.1.0.dist-info/METADATA
langextract_litellm-0.1.0.dist-info/WHEEL
langextract_litellm-0.1.0.dist-info/entry_points.txt
langextract_litellm-0.1.0.dist-info/top_level.txt
langextract_litellm-0.1.0.dist-info/RECORD
