Metadata-Version: 2.4
Name: langextract-litellm
Version: 0.1.0
Summary: LangExtract provider plugin for LiteLLM
License: Apache-2.0
Requires-Python: >=3.10
License-File: LICENSE
Requires-Dist: langextract<2.0.0,>=1.0.0
Requires-Dist: litellm>=1.40.0
Dynamic: license-file
